{

  "fields": {
    "sortPage1Fields": [
      {
        "key": "SORTId",
        "type": "label",
        "data": 0
      },
      {
        "key": "SORTRefNo",
        "type": "label",
        "data": 0
      },

      {
        "key": "OccurrenceDetails",
        "type": "textarea",
        "rows": "3",
        "cols": "50",
        "data": "",
        "templateOptions": {
          "tooltip": "Describe what happened, provide as much information as you can.",
          "label": "Occurrence Details :",
          "placeholder": "",
          "required": "yes",
          "maxlength": 500,
          "hideLabel": false,
          "maxlengthMessage": "Maximum 500 characters only allowed."
        }
      },
      {
        "key": "ReportTitle",
        "type": "input",
        "rows": "3",
        "cols": "50",
        "data": "",
        "templateOptions": {
          "label": "Report Title :",
          "placeholder": "",
          "required": "yes",
          "maxlength": 500,
          "hideLabel": false,
          "maxlengthMessage": "Maximum 500 characters only allowed.",
          "tooltip": "Give a title that briefly describes the occurrence"
        }
      },

      {
        "key": "ObjectState",
        "type": "label",
        "data": "0"
      },
      {
        "key": "Status",
        "type": "label",
        "data": "0"
      }
    ]
  }

}
